pahelee/__init__.py
pahelee/constants.py
pahelee/lib.py
pahelee/pahelee.py
pahelee-1.0.0.dist-info/DESCRIPTION.rst
pahelee-1.0.0.dist-info/METADATA
pahelee-1.0.0.dist-info/RECORD
pahelee-1.0.0.dist-info/WHEEL
pahelee-1.0.0.dist-info/entry_points.txt
pahelee-1.0.0.dist-info/metadata.json
pahelee-1.0.0.dist-info/top_level.txt
