Metadata-Version: 2.0
Name: pahelee
Version: 1.0.0
Summary: Maze generator using recursive depth first search algorithm
Home-page: https://github.com/psuzn/pahelee
Author: Sujan Poudel
Author-email: Spoudel347@gmail.com
License: BSD
Download-URL: https://github.com/psuzn/pahelee/tarball/1.0.0
Keywords: mazegeneration,opengl,pahelee
Platform: UNKNOWN
Classifier: Development Status :: 3 - Alpha
Classifier: Intended Audience :: Developers
Classifier: Programming Language :: Python :: 3
Requires-Dist: Pillow (==5.0.0)
Requires-Dist: PyOpenGL (==3.1.1a1)
Requires-Dist: setuptools (==38.5.0)
